LICENSE
MANIFEST.in
README.md
pyproject.toml
setup.py
tests/__init__.py
tests/envs/__init__.py
tests/envs/test_graph.py
tests/envs/test_grid.py
tests/envs/test_grid_3d.py
tests/envs/test_hex_grid.py
tests/factory/__init__.py
tests/factory/graph_factory.py
tests/factory/grid_factory.py
tests/factory/query_generator.py
tests/mapf/__init__.py
tests/mapf/test_cbs.py
tests/mapf/test_graph_mapf.py
tests/mapf/test_grid_mapf.py
tests/mapf/test_reservation_table.py
tests/mapf/test_space_time_a_star.py
tests/pf/__init__.py
tests/pf/test_graph_pf.py
tests/pf/test_grid_3d_pf.py
tests/pf/test_grid_pf.py
tests/pf/test_hex_grid_pf.py
tests/pf/test_pf.py
tests/pf/test_resumable_search.py
w9_pathfinding/__init__.py
w9_pathfinding/diagonal_movement.py
w9_pathfinding/envs.py
w9_pathfinding/hex_layout.py
w9_pathfinding/mapf.py
w9_pathfinding/pf.py
w9_pathfinding.egg-info/PKG-INFO
w9_pathfinding.egg-info/SOURCES.txt
w9_pathfinding.egg-info/dependency_links.txt
w9_pathfinding.egg-info/requires.txt
w9_pathfinding.egg-info/top_level.txt
w9_pathfinding/bindings/__init__.py
w9_pathfinding/bindings/cdefs.pxd
w9_pathfinding/bindings/envs.pxd
w9_pathfinding/bindings/envs.pyx
w9_pathfinding/bindings/mapf.pyx
w9_pathfinding/bindings/pf.pyx
w9_pathfinding/src/a_star.cpp
w9_pathfinding/src/bfs.cpp
w9_pathfinding/src/bi_a_star.cpp
w9_pathfinding/src/bi_bfs.cpp
w9_pathfinding/src/bi_dijkstra.cpp
w9_pathfinding/src/cbs.cpp
w9_pathfinding/src/components.cpp
w9_pathfinding/src/dfs.cpp
w9_pathfinding/src/dijkstra.cpp
w9_pathfinding/src/env.cpp
w9_pathfinding/src/gbs.cpp
w9_pathfinding/src/graph.cpp
w9_pathfinding/src/grid.cpp
w9_pathfinding/src/grid_3d.cpp
w9_pathfinding/src/hc_a_star.cpp
w9_pathfinding/src/hex_grid.cpp
w9_pathfinding/src/icts.cpp
w9_pathfinding/src/ida_star.cpp
w9_pathfinding/src/mapf.cpp
w9_pathfinding/src/multi_agent_a_star.cpp
w9_pathfinding/src/reservation_table.cpp
w9_pathfinding/src/resumable_search.cpp
w9_pathfinding/src/space_time_a_star.cpp
w9_pathfinding/src/test.cpp
w9_pathfinding/src/whc_a_star.cpp
w9_pathfinding/src/include/a_star.h
w9_pathfinding/src/include/bfs.h
w9_pathfinding/src/include/bi_a_star.h
w9_pathfinding/src/include/bi_bfs.h
