Metadata-Version: 2.4
Name: w9-pathfinding
Version: 0.1.3
Summary: Implementation of some pathfinding algorithms
Home-page: https://github.com/w9PcJLyb/w9-pathfinding
Author: w9PcJLyb
License: Apache-2.0
Project-URL: Bug Tracker, https://github.com/w9PcJLyb/w9-pathfinding/issues
Project-URL: Documentation, https://w9-pathfinding.readthedocs.io/stable
Project-URL: Release Notes, https://w9-pathfinding.readthedocs.io/stable/changelog.html
Keywords: pathfinding mapf
Requires-Python: >=3.10
License-File: LICENSE
Requires-Dist: setuptools
Requires-Dist: cython
Provides-Extra: dev
Requires-Dist: pytest; extra == "dev"
Requires-Dist: pytest-subtests; extra == "dev"
Requires-Dist: twine; extra == "dev"
Requires-Dist: numpy; extra == "dev"
Requires-Dist: matplotlib; extra == "dev"
Requires-Dist: pydantic>=2.11.0; extra == "dev"
Dynamic: author
Dynamic: description
Dynamic: description-content-type
Dynamic: home-page
Dynamic: keywords
Dynamic: license
Dynamic: license-file
Dynamic: project-url
Dynamic: provides-extra
Dynamic: requires-dist
Dynamic: requires-python
Dynamic: summary
